aiosimon_io/__init__.py
aiosimon_io/auth.py
aiosimon_io/const.py
aiosimon_io/devices.py
aiosimon_io/installations.py
aiosimon_io/logging_config.py
aiosimon_io/users.py
aiosimon_io-0.1.0.dist-info/METADATA
aiosimon_io-0.1.0.dist-info/WHEEL
aiosimon_io-0.1.0.dist-info/licenses/LICENSE
aiosimon_io-0.1.0.dist-info/RECORD
