Metadata-Version: 2.4
Name: aiosimon-io
Version: 0.1.0
Summary: An unofficial async Python client for Simon iO smart home devices
Project-URL: Homepage, https://github.com/datakatalyst/aiosimon-io
Project-URL: Documentation, https://aiosimon-io.readthedocs.io/en/latest/
Project-URL: Repository, https://github.com/datakatalyst/aiosimon-io
Project-URL: Issues, https://github.com/datakatalyst/aiosimon-io/issues
Author: Datakatalyst
License-Expression: LGPL-3.0-or-later
License-File: LICENSE
Keywords: aiohttp,asyncio,home automation,pydantic,simon,simon io,smart home
Classifier: Development Status :: 4 - Beta
Classifier: Intended Audience :: Developers
Classifier: License :: OSI Approved :: GNU Lesser General Public License v3 (LGPLv3)
Classifier: Programming Language :: Python :: 3
Classifier: Programming Language :: Python :: 3.8
Classifier: Programming Language :: Python :: 3.9
Classifier: Programming Language :: Python :: 3.10
Classifier: Programming Language :: Python :: 3.11
Classifier: Topic :: Home Automation
Classifier: Topic :: Software Development :: Libraries :: Python Modules
Requires-Python: >=3.8
Requires-Dist: aiohttp<4.0,>=3.10
Requires-Dist: asyncio<4.0,>=3.4
Requires-Dist: pydantic<3.0,>=2.10
Provides-Extra: build
Requires-Dist: build<2.0,>=1.2; extra == 'build'
Requires-Dist: twine<7.0,>=6.1; extra == 'build'
Provides-Extra: dev
Requires-Dist: black<25.0,>=24.8; extra == 'dev'
Requires-Dist: flake8<8.0,>=7.1; extra == 'dev'
Requires-Dist: isort<6.0,>=5.13; extra == 'dev'
Requires-Dist: mypy<2.0,>=1.14; extra == 'dev'
Requires-Dist: validate-pyproject<1.0,>=0.24; extra == 'dev'
Provides-Extra: docs
Requires-Dist: sphinx-autodoc-typehints<3.0,>=2.0; extra == 'docs'
Requires-Dist: sphinx-rtd-theme<4.0,>=3.0; extra == 'docs'
Requires-Dist: sphinx<8.0,>=7.1; extra == 'docs'
Provides-Extra: test
Requires-Dist: aioresponses<1.0,>=0.7; extra == 'test'
Requires-Dist: pytest-asyncio<1.0,>=0.24; extra == 'test'
Requires-Dist: pytest-cov<6.0,>=5.0; extra == 'test'
Requires-Dist: pytest-mock<4.0,>=3.14; extra == 'test'
Requires-Dist: pytest<9.0,>=8.3; extra == 'test'
